preciso/HDF5.py
preciso/Logo-Figures.png
preciso/__init__.py
preciso/distributions.py
preciso/preciso.py
preciso/results.py
preciso/run.py
preciso/bin/PreciSo-linux
preciso/bin/log.log
preciso/bin/preciso-macOS
preciso/bin/preciso.exe
Preciso-1.0.9.dist-info/LICENCE.md
Preciso-1.0.9.dist-info/METADATA
Preciso-1.0.9.dist-info/WHEEL
Preciso-1.0.9.dist-info/top_level.txt
Preciso-1.0.9.dist-info/RECORD
