Metadata-Version: 2.1
Name: Preciso
Version: 1.0.9
Summary: A package for modelling precipitation in alloys.
Home-page: https://arnall.gitlab.io/preciso/
Author: Michel Perez
Author-email: michel.perez@insa-lyon.fr
Classifier: Programming Language :: Python :: 3
Classifier: Operating System :: OS Independent
Requires-Python: >=3.6
License-File: LICENCE.md
Requires-Dist: pandas
Requires-Dist: numpy
Requires-Dist: matplotlib
Requires-Dist: jinja2
Requires-Dist: pytest
Requires-Dist: tables
Requires-Dist: h5py
Requires-Dist: jupyter
